setup.py
sentry_app/__init__.py
sentry_app/console.py
sentry_app/server_status/__init__.py
sentry_app/server_status/docker_status.py
sentry_app/server_status/process_status.py
sentry_app/server_status/status.py
sentry_app/server_status/usage.py
sentry_app/server_status/utils.py
sentry_app/utils/__init__.py
sentry_app/utils/functional.py
sentry_app/utils/zip_content.py
sentryapp.egg-info/PKG-INFO
sentryapp.egg-info/SOURCES.txt
sentryapp.egg-info/dependency_links.txt
sentryapp.egg-info/entry_points.txt
sentryapp.egg-info/requires.txt
sentryapp.egg-info/top_level.txt